puzzel_sms_gateway_client/__init__.py
puzzel_sms_gateway_client/_exceptions.py
puzzel_sms_gateway_client/puzzel_sms_gateway_client.py
puzzel_sms_gateway_client/schemas.py
puzzel_sms_gateway_client-2.0.2.dist-info/LICENSE
puzzel_sms_gateway_client-2.0.2.dist-info/METADATA
puzzel_sms_gateway_client-2.0.2.dist-info/WHEEL
puzzel_sms_gateway_client-2.0.2.dist-info/RECORD
