Metadata-Version: 2.1
Name: puzzel_sms_gateway_client
Version: 2.0.2
Summary: Python client for Puzzel SMS Gateway
Home-page: https://www.puzzel.com
License: MIT
Keywords: puzzel,sms,smsgw,sms-gw,smsapi,sms-api,sms-gateway,sms-gateway-client,gsm
Author: Lewi Lie Uberg
Author-email: lewi.uberg@puzzel.com
Maintainer: Lewi Uberg
Maintainer-email: lewi.uberg@puzzel.com
Requires-Python: >=3.10.5,<4.0.0
Classifier: Development Status :: 5 - Production/Stable
Classifier: Intended Audience :: Developers
Classifier: License :: OSI Approved :: MIT License
Classifier: Programming Language :: Python :: 3
Classifier: Programming Language :: Python :: 3.11
Classifier: Programming Language :: Python :: 3.12
Classifier: Programming Language :: Python :: 3.10
Classifier: Topic :: Software Development :: Libraries :: Python Modules
Requires-Dist: fastapi (>=0.78.0,<0.79.0)
Requires-Dist: pydantic (>=1.9.1,<2.0.0)
Requires-Dist: requests (>=2.28.1,<3.0.0)
Project-URL: Documentation, https://github.com/PuzzelSolutions/SMS
Project-URL: Repository, https://github.com/PuzzelSolutions/smsgw-client-python
